rtl/ALU/divider.v
`timescale 1ns / 1ps
//////////////////////////////////////////////////////////////////////////////////
// Company: 
// Engineer: 
// 
// Create Date: 2026/03/08 17:37:44
// Design Name: 
// Module Name: div
// Project Name: 
// Target Devices: 
// Tool Versions: 
// Description: 
// 
// Dependencies: 
// 
// Revision:
// Revision 0.01 - File Created
// Additional Comments:
// 
//////////////////////////////////////////////////////////////////////////////////
module divider_seq (
    input  wire        clk,
    input  wire        rst_n,
    input  wire        start,      // 开始信号
    input  wire [31:0] dividend,   // 被除数
    input  wire [31:0] divisor,    // 除数
    output reg  [31:0] quotient,   // 商
    output reg  [31:0] remainder,  // 余数
    output reg         ready,      // 空闲/完成信号
    output reg         dbz         // 除以0错误 (Divide by Zero)
);

    // 状态定义
    localparam IDLE = 2'b00;
    localparam CALC = 2'b01;
    localparam DONE = 2'b10;

    reg [1:0]  state;
    reg [5:0]  count;
    
    // 核心寄存器：使用一个64位的寄存器来合并处理余数和商
    // 高32位初始为0（最终变为余数），低32位初始为被除数（最终变为商）
    reg [63:0] temp_reg; 
    reg [31:0] temp_divisor;

    wire [63:0] shifted_reg = temp_reg << 1;
    always @(posedge clk or negedge rst_n) begin
        if (!rst_n) begin
            state        <= IDLE;
            ready        <= 1'b1;
            dbz          <= 1'b0;
            quotient     <= 32'd0;
            remainder    <= 32'd0;
            count        <= 6'd0;
            temp_reg     <= 64'd0;
            temp_divisor <= 32'd0;
        end else begin
            case (state)
                IDLE: begin
                    ready <= 1'b1;
                    if (start) begin
                        ready <= 1'b0;
                        if (divisor == 32'd0) begin
                            dbz   <= 1'b1;  // 错误：除数为0
                            state <= DONE;
                        end else begin
                            dbz          <= 1'b0;
                            count        <= 6'd0;
                            temp_reg     <= {32'd0, dividend}; // 高32位清零，低32位放被除数
                            temp_divisor <= divisor;
                            state        <= CALC;
                        end
                    end
                end

                CALC: begin
                    if (count < 6'd32) begin                     
                        if (shifted_reg[63:32] >= temp_divisor) begin
                            // 够减：高32位减去除数，低位补1
                            temp_reg <= {shifted_reg[63:32] - temp_divisor, shifted_reg[31:1], 1'b1};
                        end else begin
                            // 不够减：直接保留左移后的结果（最低位本来就是0）
                            temp_reg <= shifted_reg;
                        end
                        count <= count + 6'd1;
                    end else begin
                        state <= DONE;
                    end
                end

                DONE: begin
                    quotient  <= temp_reg[31:0];  // 低32位是商
                    remainder <= temp_reg[63:32]; // 高32位是余数
                    ready     <= 1'b1;
                    state     <= IDLE;
                end

                default: state <= IDLE;
            endcase
        end
    end

endmodule

sim/ALU/tb_divider.v
`timescale 1ns / 1ps
//////////////////////////////////////////////////////////////////////////////////
// Company: 
// Engineer: 
// 
// Create Date: 2026/03/08 17:38:02
// Design Name: 
// Module Name: tb_div
// Project Name: 
// Target Devices: 
// Tool Versions: 
// Description: 
// 
// Dependencies: 
// 
// Revision:
// Revision 0.01 - File Created
// Additional Comments:
// 
//////////////////////////////////////////////////////////////////////////////////
module tb_divider_seq();

    // 信号定义
    reg         clk;
    reg         rst_n;
    reg         start;
    reg  [31:0] dividend;
    reg  [31:0] divisor;
    
    wire [31:0] quotient;
    wire [31:0] remainder;
    wire        ready;
    wire        dbz;

    // 实例化除法器
    divider_seq uut (
        .clk(clk),
        .rst_n(rst_n),
        .start(start),
        .dividend(dividend),
        .divisor(divisor),
        .quotient(quotient),
        .remainder(remainder),
        .ready(ready),
        .dbz(dbz)
    );

    // 1. 时钟生成 (100MHz)
    initial clk = 0;
    always #5 clk = ~clk;

    // 2. 仿真过程
    initial begin
        // 初始化
        rst_n = 0;
        start = 0;
        dividend = 0;
        divisor = 0;

        // 复位
        #20 rst_n = 1;
        #10;

        $display("========================================");
        $display("Starting Sequential Divider Test...");
        $display("========================================");

        // --- Case 1: 整除 ---
        drive_divider(32'd100, 32'd10);
        check_result("Perfect Division (100/10)");

        // --- Case 2: 带余数除法 ---
        drive_divider(32'd10, 32'd3);
        check_result("Division with Remainder (10/3)");

        // --- Case 3: 被除数小于除数 ---
        drive_divider(32'd5, 32'd12);
        check_result("Small Dividend (5/12)");

        // --- Case 4: 除以0测试 ---
        drive_divider(32'd100, 32'd0);
        if (dbz) $display("[PASS] Divide by Zero detected correctly.");
        else     $display("[FAIL] Divide by Zero NOT detected!");

        // --- Case 5: 随机压力测试 ---
        repeat(10) begin
            drive_divider($urandom % 1000, ($urandom % 50) + 1); // 保证除数不为0
            check_result("Random Test");
        end

        $display("========================================");
        $display("All Division Tests Finished.");
        $display("========================================");
        $finish;
    end

    // 任务：驱动除法器
    task drive_divider(input [31:0] d_end, input [31:0] d_sor);
        begin
            @(posedge clk);
            dividend = d_end;
            divisor = d_sor;
            start = 1;
            @(posedge clk);
            start = 0;
            
            // 等待计算完成
            wait(ready == 1);
            @(posedge clk);
        end
    endtask

    // 任务：验证结果
    task check_result(input [8*40:1] test_name);
        reg [31:0] ref_q;
        reg [31:0] ref_r;
        begin
            ref_q = dividend / divisor;
            ref_r = dividend % divisor;
            
            // 验证恒等式: Dividend = Q*D + R
            if ((quotient === ref_q) && (remainder === ref_r)) begin
                $display("[PASS] %s: %d / %d = %d ... %d", 
                         test_name, dividend, divisor, quotient, remainder);
            end else begin
                $display("[FAIL] %s: %d / %d | Expected %d...%d, Got %d...%d", 
                         test_name, dividend, divisor, ref_q, ref_r, quotient, remainder);
            end
        end
    endtask

endmodule

sim/vcd/dump_div.vcd
$date
	Mon Aug 10 22:11:45 2026
$end
$version
	Icarus Verilog
$end
$timescale
	1ps
$end
$scope module tb_divider_seq $end
$scope module uut $end
$var wire 1 ! clk $end
$var wire 32 " dividend [31:0] $end
$var wire 32 # divisor [31:0] $end
$var wire 1 $ rst_n $end
$var wire 1 % start $end
$var wire 64 & shifted_reg [63:0] $end
$var parameter 2 ' CALC $end
$var parameter 2 ( DONE $end
$var parameter 2 ) IDLE $end
$var reg 6 * count [5:0] $end
$var reg 1 + dbz $end
$var reg 32 , quotient [31:0] $end
$var reg 1 - ready $end
$var reg 32 . remainder [31:0] $end
$var reg 2 / state [1:0] $end
$var reg 32 0 temp_divisor [31:0] $end
$var reg 64 1 temp_reg [63:0] $end
$upscope $end
$upscope $end
$enddefinitions $end
$comment Show the parameter values. $end
$dumpall
b0 )
b10 (
b1 '
$end
#0
$dumpvars
b0 1
b0 0
b0 /
b0 .
1-
b0 ,
0+
b0 *
b0 &
0%
0$
b0 #
b0 "
0!
$end
#5000
1!
#10000
0!
#15000
1!
#20000
0!
1$
#25000
1!
#30000
0!
#35000
b11001000 &
b1 /
b1010 0
b1100100 1
0-
1%
b1010 #
b1100100 "
1!
#40000
0!
#45000
b110010000 &
b1 *
b11001000 1
0%
1!
#50000
0!
#55000
b1100100000 &
b10 *
b110010000 1
1!
#60000
0!
#65000
b11001000000 &
b11 *
b1100100000 1
1!
#70000
0!
#75000
b110010000000 &
b100 *
b11001000000 1
1!
#80000
0!
#85000
b1100100000000 &
b101 *
b110010000000 1
1!
#90000
0!
#95000
b11001000000000 &
b110 *
b1100100000000 1
1!
#100000
0!
#105000
b110010000000000 &
b111 *
b11001000000000 1
1!
#110000
0!
#115000
b1100100000000000 &
b1000 *
b110010000000000 1
1!
#120000
0!
#125000
b11001000000000000 &
b1001 *
b1100100000000000 1
1!
#130000
0!
#135000
b110010000000000000 &
b1010 *
b11001000000000000 1
1!
#140000
0!
#145000
b1100100000000000000 &
b1011 *
b110010000000000000 1
1!
#150000
0!
#155000
b11001000000000000000 &
b1100 *
b1100100000000000000 1
1!
#160000
0!
#165000
b110010000000000000000 &
b1101 *
b11001000000000000000 1
1!
#170000
0!
#175000
b1100100000000000000000 &
b1110 *
b110010000000000000000 1
1!
#180000
0!
#185000
b11001000000000000000000 &
b1111 *
b1100100000000000000000 1
1!
#190000
0!
#195000
b110010000000000000000000 &
b10000 *
b11001000000000000000000 1
1!
#200000
0!
#205000
b1100100000000000000000000 &
b10001 *
b110010000000000000000000 1
1!
#210000
0!
#215000
b11001000000000000000000000 &
b10010 *
b1100100000000000000000000 1
1!
#220000
0!
#225000
b110010000000000000000000000 &
b10011 *
b11001000000000000000000000 1
1!
#230000
0!
#235000
b1100100000000000000000000000 &
b10100 *
b110010000000000000000000000 1
1!
#240000
0!
#245000
b11001000000000000000000000000 &
b10101 *
b1100100000000000000000000000 1
1!
#250000
0!
#255000
b110010000000000000000000000000 &
b10110 *
b11001000000000000000000000000 1
1!
#260000
0!
#265000
b1100100000000000000000000000000 &
b10111 *
b110010000000000000000000000000 1
1!
#270000
0!
#275000
b11001000000000000000000000000000 &
b11000 *
b1100100000000000000000000000000 1
1!
#280000
0!
#285000
b110010000000000000000000000000000 &
b11001 *
b11001000000000000000000000000000 1
1!
#290000
0!
#295000
b1100100000000000000000000000000000 &
b11010 *
b110010000000000000000000000000000 1
1!
#300000
0!
#305000
b11001000000000000000000000000000000 &
b11011 *
b1100100000000000000000000000000000 1
1!
#310000
0!
#315000
b110010000000000000000000000000000000 &
b11100 *
b11001000000000000000000000000000000 1
1!
#320000
0!
#325000
b10100000000000000000000000000000010 &
b11101 *
b1010000000000000000000000000000001 1
1!
#330000
0!
#335000
b101000000000000000000000000000000100 &
b11110 *
b10100000000000000000000000000000010 1
1!
#340000
0!
#345000
b1010 &
b11111 *
b101 1
1!
#350000
0!
#355000
b10100 &
b100000 *
b1010 1
1!
#360000
0!
#365000
b10 /
1!
#370000
0!
#375000
b0 /
1-
b1010 ,
1!
#380000
0!
#385000
1!
#390000
0!
#395000
b1 /
b11 0
b0 *
0-
1%
b11 #
b1010 "
1!
#400000
0!
#405000
b101000 &
b1 *
b10100 1
0%
1!
#410000
0!
#415000
b1010000 &
b10 *
b101000 1
1!
#420000
0!
#425000
b10100000 &
b11 *
b1010000 1
1!
#430000
0!
#435000
b101000000 &
b100 *
b10100000 1
1!
#440000
0!
#445000
b1010000000 &
b101 *
b101000000 1
1!
#450000
0!
#455000
b10100000000 &
b110 *
b1010000000 1
1!
#460000
0!
#465000
b101000000000 &
b111 *
b10100000000 1
1!
#470000
0!
#475000
b1010000000000 &
b1000 *
b101000000000 1
1!
#480000
0!
#485000
b10100000000000 &
b1001 *
b1010000000000 1
1!
#490000
0!
#495000
b101000000000000 &
b1010 *
b10100000000000 1
1!
#500000
0!
#505000
b1010000000000000 &
b1011 *
b101000000000000 1
1!
#510000
0!
#515000
b10100000000000000 &
b1100 *
b1010000000000000 1
1!
#520000
0!
#525000
b101000000000000000 &
b1101 *
b10100000000000000 1
1!
#530000
0!
#535000
b1010000000000000000 &
b1110 *
b101000000000000000 1
1!
#540000
0!
#545000
b10100000000000000000 &
b1111 *
b1010000000000000000 1
1!
#550000
0!
#555000
b101000000000000000000 &
b10000 *
b10100000000000000000 1
1!
#560000
0!
#565000
b1010000000000000000000 &
b10001 *
b101000000000000000000 1
1!
#570000
0!
#575000
b10100000000000000000000 &
b10010 *
b1010000000000000000000 1
1!
#580000
0!
#585000
b101000000000000000000000 &
b10011 *
b10100000000000000000000 1
1!
#590000
0!
#595000
b1010000000000000000000000 &
b10100 *
b101000000000000000000000 1
1!
#600000
0!
#605000
b10100000000000000000000000 &
b10101 *
b1010000000000000000000000 1
1!
#610000
0!
#615000
b101000000000000000000000000 &
b10110 *
b10100000000000000000000000 1
1!
#620000
0!
#625000
b1010000000000000000000000000 &
b10111 *
b101000000000000000000000000 1
1!
#630000
0!
#635000
b10100000000000000000000000000 &
b11000 *
b1010000000000000000000000000 1
1!
#640000
0!
#645000
b101000000000000000000000000000 &
b11001 *
b10100000000000000000000000000 1
1!
#650000
0!
#655000
b1010000000000000000000000000000 &
b11010 *
b101000000000000000000000000000 1
1!
#660000
0!
#665000
b10100000000000000000000000000000 &
b11011 *
b1010000000000000000000000000000 1
1!
#670000
0!
#675000
b101000000000000000000000000000000 &
b11100 *
b10100000000000000000000000000000 1
1!
#680000
0!
#685000
b1010000000000000000000000000000000 &
b11101 *
b101000000000000000000000000000000 1
1!
#690000
0!
#695000
b10100000000000000000000000000000000 &
b11110 *
b1010000000000000000000000000000000 1
1!
#700000
0!
#705000
b10000000000000000000000000000000010 &
b11111 *
b1000000000000000000000000000000001 1
1!
#710000
0!
#715000
b1000000000000000000000000000000110 &
b100000 *
b100000000000000000000000000000011 1
1!
#720000
0!
#725000
b10 /
1!
#730000
0!
#735000
b0 /
1-
b1 .
b11 ,
1!
#740000
0!
#745000
1!
#750000
0!
#755000
b1010 &
b1 /
b1100 0
b101 1
b0 *
0-
1%
b1100 #
b101 "
1!
#760000
0!
#765000
b10100 &
b1 *
b1010 1
0%
1!
#770000
0!
#775000
b101000 &
b10 *
b10100 1
1!
#780000
0!
#785000
b1010000 &
b11 *
b101000 1
1!
#790000
0!
#795000
b10100000 &
b100 *
b1010000 1
1!
#800000
0!
#805000
b101000000 &
b101 *
b10100000 1
1!
#810000
0!
#815000
b1010000000 &
b110 *
b101000000 1
1!
#820000
0!
#825000
b10100000000 &
b111 *
b1010000000 1
1!
#830000
0!
#835000
b101000000000 &
b1000 *
b10100000000 1
1!
#840000
0!
#845000
b1010000000000 &
b1001 *
b101000000000 1
1!
#850000
0!
#855000
b10100000000000 &
b1010 *
b1010000000000 1
1!
#860000
0!
#865000
b101000000000000 &
b1011 *
b10100000000000 1
1!
#870000
0!
#875000
b1010000000000000 &
b1100 *
b101000000000000 1
1!
#880000
0!
#885000
b10100000000000000 &
b1101 *
b1010000000000000 1
1!
#890000
0!
#895000
b101000000000000000 &
b1110 *
b10100000000000000 1
1!
#900000
0!
#905000
b1010000000000000000 &
b1111 *
b101000000000000000 1
1!
#910000
0!
#915000
b10100000000000000000 &
b10000 *
b1010000000000000000 1
1!
#920000
0!
#925000
b101000000000000000000 &
b10001 *
b10100000000000000000 1
1!
#930000
0!
#935000
b1010000000000000000000 &
b10010 *
b101000000000000000000 1
1!
#940000
0!
#945000
b10100000000000000000000 &
b10011 *
b1010000000000000000000 1
1!
#950000
0!
#955000
b101000000000000000000000 &
b10100 *
b10100000000000000000000 1
1!
#960000
0!
#965000
b1010000000000000000000000 &
b10101 *
b101000000000000000000000 1
1!
#970000
0!
#975000
b10100000000000000000000000 &
b10110 *
b1010000000000000000000000 1
1!
#980000
0!
#985000
b101000000000000000000000000 &
b10111 *
b10100000000000000000000000 1
1!
#990000
0!
#995000
b1010000000000000000000000000 &
b11000 *
b101000000000000000000000000 1
1!
#1000000
0!
#1005000
b10100000000000000000000000000 &
b11001 *
b1010000000000000000000000000 1
1!
#1010000
0!
#1015000
b101000000000000000000000000000 &
b11010 *
b10100000000000000000000000000 1
1!
#1020000
0!
#1025000
b1010000000000000000000000000000 &
b11011 *
b101000000000000000000000000000 1
1!
#1030000
0!
#1035000
b10100000000000000000000000000000 &
b11100 *
b1010000000000000000000000000000 1
1!
#1040000
0!
#1045000
b101000000000000000000000000000000 &
b11101 *
b10100000000000000000000000000000 1
1!
#1050000
0!
#1055000
b1010000000000000000000000000000000 &
b11110 *
b101000000000000000000000000000000 1
1!
#1060000
0!
#1065000
b10100000000000000000000000000000000 &
b11111 *
b1010000000000000000000000000000000 1
1!
#1070000
0!
#1075000
b101000000000000000000000000000000000 &
b100000 *
b10100000000000000000000000000000000 1
1!
#1080000
0!
#1085000
b10 /
1!
#1090000
0!
#1095000
b0 /
1-
b101 .
b0 ,
1!
#1100000
0!
#1105000
1!
#1110000
0!
#1115000
b10 /
1+
0-
1%
b0 #
b1100100 "
1!
#1120000
0!
#1125000
b0 /
1-
0%
1!
#1130000
0!
#1135000
1!
#1140000
0!
#1145000
b1100011000 &
b1 /
b110010 0
b110001100 1
b0 *
0+
0-
1%
b110010 #
b110001100 "
1!
#1150000
0!
#1155000
b11000110000 &
b1 *
b1100011000 1
0%
1!
#1160000
0!
#1165000
b110001100000 &
b10 *
b11000110000 1
1!
#1170000
0!
#1175000
b1100011000000 &
b11 *
b110001100000 1
1!
#1180000
0!
#1185000
b11000110000000 &
b100 *
b1100011000000 1
1!
#1190000
0!
#1195000
b110001100000000 &
b101 *
b11000110000000 1
1!
#1200000
0!
#1205000
b1100011000000000 &
b110 *
b110001100000000 1
1!
#1210000
0!
#1215000
b11000110000000000 &
b111 *
b1100011000000000 1
1!
#1220000
0!
#1225000
b110001100000000000 &
b1000 *
b11000110000000000 1
1!
#1230000
0!
#1235000
b1100011000000000000 &
b1001 *
b110001100000000000 1
1!
#1240000
0!
#1245000
b11000110000000000000 &
b1010 *
b1100011000000000000 1
1!
#1250000
0!
#1255000
b110001100000000000000 &
b1011 *
b11000110000000000000 1
1!
#1260000
0!
#1265000
b1100011000000000000000 &
b1100 *
b110001100000000000000 1
1!
#1270000
0!
#1275000
b11000110000000000000000 &
b1101 *
b1100011000000000000000 1
1!
#1280000
0!
#1285000
b110001100000000000000000 &
b1110 *
b11000110000000000000000 1
1!
#1290000
0!
#1295000
b1100011000000000000000000 &
b1111 *
b110001100000000000000000 1
1!
#1300000
0!
#1305000
b11000110000000000000000000 &
b10000 *
b1100011000000000000000000 1
1!
#1310000
0!
#1315000
b110001100000000000000000000 &
b10001 *
b11000110000000000000000000 1
1!
#1320000
0!
#1325000
b1100011000000000000000000000 &
b10010 *
b110001100000000000000000000 1
1!
#1330000
0!
#1335000
b11000110000000000000000000000 &
b10011 *
b1100011000000000000000000000 1
1!
#1340000
0!
#1345000
b110001100000000000000000000000 &
b10100 *
b11000110000000000000000000000 1
1!
#1350000
0!
#1355000
b1100011000000000000000000000000 &
b10101 *
b110001100000000000000000000000 1
1!
#1360000
0!
#1365000
b11000110000000000000000000000000 &
b10110 *
b1100011000000000000000000000000 1
1!
#1370000
0!
#1375000
b110001100000000000000000000000000 &
b10111 *
b11000110000000000000000000000000 1
1!
#1380000
0!
#1385000
b1100011000000000000000000000000000 &
b11000 *
b110001100000000000000000000000000 1
1!
#1390000
0!
#1395000
b11000110000000000000000000000000000 &
b11001 *
b1100011000000000000000000000000000 1
1!
#1400000
0!
#1405000
b110001100000000000000000000000000000 &
b11010 *
b11000110000000000000000000000000000 1
1!
#1410000
0!
#1415000
b1100011000000000000000000000000000000 &
b11011 *
b110001100000000000000000000000000000 1
1!
#1420000
0!
#1425000
b11000110000000000000000000000000000000 &
b11100 *
b1100011000000000000000000000000000000 1
1!
#1430000
0!
#1435000
b110001100000000000000000000000000000000 &
b11101 *
b11000110000000000000000000000000000000 1
1!
#1440000
0!
#1445000
b110001000000000000000000000000000000010 &
b11110 *
b11000100000000000000000000000000000001 1
1!
#1450000
0!
#1455000
b110000000000000000000000000000000000110 &
b11111 *
b11000000000000000000000000000000000011 1
1!
#1460000
0!
#1465000
b101110000000000000000000000000000001110 &
b100000 *
b10111000000000000000000000000000000111 1
1!
#1470000
0!
#1475000
b10 /
1!
#1480000
0!
#1485000
b0 /
1-
b101110 .
b111 ,
1!
#1490000
0!
#1495000
1!
#1500000
0!
#1505000
b1100110010 &
b1 /
b101000 0
b110011001 1
b0 *
0-
1%
b101000 #
b110011001 "
1!
#1510000
0!
#1515000
b11001100100 &
b1 *
b1100110010 1
0%
1!
#1520000
0!
#1525000
b110011001000 &
b10 *
b11001100100 1
1!
#1530000
0!
#1535000
b1100110010000 &
b11 *
b110011001000 1
1!
#1540000
0!
#1545000
b11001100100000 &
b100 *
b1100110010000 1
1!
#1550000
0!
#1555000
b110011001000000 &
b101 *
b11001100100000 1
1!
#1560000
0!
#1565000
b1100110010000000 &
b110 *
b110011001000000 1
1!
#1570000
0!
#1575000
b11001100100000000 &
b111 *
b1100110010000000 1
1!
#1580000
0!
#1585000
b110011001000000000 &
b1000 *
b11001100100000000 1
1!
#1590000
0!
#1595000
b1100110010000000000 &
b1001 *
b110011001000000000 1
1!
#1600000
0!
#1605000
b11001100100000000000 &
b1010 *
b1100110010000000000 1
1!
#1610000
0!
#1615000
b110011001000000000000 &
b1011 *
b11001100100000000000 1
1!
#1620000
0!
#1625000
b1100110010000000000000 &
b1100 *
b110011001000000000000 1
1!
#1630000
0!
#1635000
b11001100100000000000000 &
b1101 *
b1100110010000000000000 1
1!
#1640000
0!
#1645000
b110011001000000000000000 &
b1110 *
b11001100100000000000000 1
1!
#1650000
0!
#1655000
b1100110010000000000000000 &
b1111 *
b110011001000000000000000 1
1!
#1660000
0!
#1665000
b11001100100000000000000000 &
b10000 *
b1100110010000000000000000 1
1!
#1670000
0!
#1675000
b110011001000000000000000000 &
b10001 *
b11001100100000000000000000 1
1!
#1680000
0!
#1685000
b1100110010000000000000000000 &
b10010 *
b110011001000000000000000000 1
1!
#1690000
0!
#1695000
b11001100100000000000000000000 &
b10011 *
b1100110010000000000000000000 1
1!
#1700000
0!
#1705000
b110011001000000000000000000000 &
b10100 *
b11001100100000000000000000000 1
1!
#1710000
0!
#1715000
b1100110010000000000000000000000 &
b10101 *
b110011001000000000000000000000 1
1!
#1720000
0!
#1725000
b11001100100000000000000000000000 &
b10110 *
b1100110010000000000000000000000 1
1!
#1730000
0!
#1735000
b110011001000000000000000000000000 &
b10111 *
b11001100100000000000000000000000 1
1!
#1740000
0!
#1745000
b1100110010000000000000000000000000 &
b11000 *
b110011001000000000000000000000000 1
1!
#1750000
0!
#1755000
b11001100100000000000000000000000000 &
b11001 *
b1100110010000000000000000000000000 1
1!
#1760000
0!
#1765000
b110011001000000000000000000000000000 &
b11010 *
b11001100100000000000000000000000000 1
1!
#1770000
0!
#1775000
b1100110010000000000000000000000000000 &
b11011 *
b110011001000000000000000000000000000 1
1!
#1780000
0!
#1785000
b11001100100000000000000000000000000000 &
b11100 *
b1100110010000000000000000000000000000 1
1!
#1790000
0!
#1795000
b1011001000000000000000000000000000010 &
b11101 *
b101100100000000000000000000000000001 1
1!
#1800000
0!
#1805000
b10110010000000000000000000000000000100 &
b11110 *
b1011001000000000000000000000000000010 1
1!
#1810000
0!
#1815000
b100100000000000000000000000000001010 &
b11111 *
b10010000000000000000000000000000101 1
1!
#1820000
0!
#1825000
b1001000000000000000000000000000010100 &
b100000 *
b100100000000000000000000000000001010 1
1!
#1830000
0!
#1835000
b10 /
1!
#1840000
0!
#1845000
b0 /
1-
b1001 .
b1010 ,
1!
#1850000
0!
#1855000
1!
#1860000
0!
#1865000
b10010111010 &
b1 /
b110 0
b1001011101 1
b0 *
0-
1%
b110 #
b1001011101 "
1!
#1870000
0!
#1875000
b100101110100 &
b1 *
b10010111010 1
0%
1!
#1880000
0!
#1885000
b1001011101000 &
b10 *
b100101110100 1
1!
#1890000
0!
#1895000
b10010111010000 &
b11 *
b1001011101000 1
1!
#1900000
0!
#1905000
b100101110100000 &
b100 *
b10010111010000 1
1!
#1910000
0!
#1915000
b1001011101000000 &
b101 *
b100101110100000 1
1!
#1920000
0!
#1925000
b10010111010000000 &
b110 *
b1001011101000000 1
1!
#1930000
0!
#1935000
b100101110100000000 &
b111 *
b10010111010000000 1
1!
#1940000
0!
#1945000
b1001011101000000000 &
b1000 *
b100101110100000000 1
1!
#1950000
0!
#1955000
b10010111010000000000 &
b1001 *
b1001011101000000000 1
1!
#1960000
0!
#1965000
b100101110100000000000 &
b1010 *
b10010111010000000000 1
1!
#1970000
0!
#1975000
b1001011101000000000000 &
b1011 *
b100101110100000000000 1
1!
#1980000
0!
#1985000
b10010111010000000000000 &
b1100 *
b1001011101000000000000 1
1!
#1990000
0!
#1995000
b100101110100000000000000 &
b1101 *
b10010111010000000000000 1
1!
#2000000
0!
#2005000
b1001011101000000000000000 &
b1110 *
b100101110100000000000000 1
1!
#2010000
0!
#2015000
b10010111010000000000000000 &
b1111 *
b1001011101000000000000000 1
1!
#2020000
0!
#2025000
b100101110100000000000000000 &
b10000 *
b10010111010000000000000000 1
1!
#2030000
0!
#2035000
b1001011101000000000000000000 &
b10001 *
b100101110100000000000000000 1
1!
#2040000
0!
#2045000
b10010111010000000000000000000 &
b10010 *
b1001011101000000000000000000 1
1!
#2050000
0!
#2055000
b100101110100000000000000000000 &
b10011 *
b10010111010000000000000000000 1
1!
#2060000
0!
#2065000
b1001011101000000000000000000000 &
b10100 *
b100101110100000000000000000000 1
1!
#2070000
0!
#2075000
b10010111010000000000000000000000 &
b10101 *
b1001011101000000000000000000000 1
1!
#2080000
0!
#2085000
b100101110100000000000000000000000 &
b10110 *
b10010111010000000000000000000000 1
1!
#2090000
0!
#2095000
b1001011101000000000000000000000000 &
b10111 *
b100101110100000000000000000000000 1
1!
#2100000
0!
#2105000
b10010111010000000000000000000000000 &
b11000 *
b1001011101000000000000000000000000 1
1!
#2110000
0!
#2115000
b100101110100000000000000000000000000 &
b11001 *
b10010111010000000000000000000000000 1
1!
#2120000
0!
#2125000
b11011101000000000000000000000000010 &
b11010 *
b1101110100000000000000000000000001 1
1!
#2130000
0!
#2135000
b111010000000000000000000000000110 &
b11011 *
b11101000000000000000000000000011 1
1!
#2140000
0!
#2145000
b1110100000000000000000000000001100 &
b11100 *
b111010000000000000000000000000110 1
1!
#2150000
0!
#2155000
b11101000000000000000000000000011000 &
b11101 *
b1110100000000000000000000000001100 1
1!
#2160000
0!
#2165000
b1010000000000000000000000000110010 &
b11110 *
b101000000000000000000000000011001 1
1!
#2170000
0!
#2175000
b10100000000000000000000000001100100 &
b11111 *
b1010000000000000000000000000110010 1
1!
#2180000
0!
#2185000
b101000000000000000000000000011001000 &
b100000 *
b10100000000000000000000000001100100 1
1!
#2190000
0!
#2195000
b10 /
1!
#2200000
0!
#2205000
b0 /
1-
b101 .
b1100100 ,
1!
#2210000
0!
#2215000
1!
#2220000
0!
#2225000
b10101001010 &
b1 /
b100011 0
b1010100101 1
b0 *
0-
1%
b100011 #
b1010100101 "
1!
#2230000
0!
#2235000
b101010010100 &
b1 *
b10101001010 1
0%
1!
#2240000
0!
#2245000
b1010100101000 &
b10 *
b101010010100 1
1!
#2250000
0!
#2255000
b10101001010000 &
b11 *
b1010100101000 1
1!
#2260000
0!
#2265000
b101010010100000 &
b100 *
b10101001010000 1
1!
#2270000
0!
#2275000
b1010100101000000 &
b101 *
b101010010100000 1
1!
#2280000
0!
#2285000
b10101001010000000 &
b110 *
b1010100101000000 1
1!
#2290000
0!
#2295000
b101010010100000000 &
b111 *
b10101001010000000 1
1!
#2300000
0!
#2305000
b1010100101000000000 &
b1000 *
b101010010100000000 1
1!
#2310000
0!
#2315000
b10101001010000000000 &
b1001 *
b1010100101000000000 1
1!
#2320000
0!
#2325000
b101010010100000000000 &
b1010 *
b10101001010000000000 1
1!
#2330000
0!
#2335000
b1010100101000000000000 &
b1011 *
b101010010100000000000 1
1!
#2340000
0!
#2345000
b10101001010000000000000 &
b1100 *
b1010100101000000000000 1
1!
#2350000
0!
#2355000
b101010010100000000000000 &
b1101 *
b10101001010000000000000 1
1!
#2360000
0!
#2365000
b1010100101000000000000000 &
b1110 *
b101010010100000000000000 1
1!
#2370000
0!
#2375000
b10101001010000000000000000 &
b1111 *
b1010100101000000000000000 1
1!
#2380000
0!
#2385000
b101010010100000000000000000 &
b10000 *
b10101001010000000000000000 1
1!
#2390000
0!
#2395000
b1010100101000000000000000000 &
b10001 *
b101010010100000000000000000 1
1!
#2400000
0!
#2405000
b10101001010000000000000000000 &
b10010 *
b1010100101000000000000000000 1
1!
#2410000
0!
#2415000
b101010010100000000000000000000 &
b10011 *
b10101001010000000000000000000 1
1!
#2420000
0!
#2425000
b1010100101000000000000000000000 &
b10100 *
b101010010100000000000000000000 1
1!
#2430000
0!
#2435000
b10101001010000000000000000000000 &
b10101 *
b1010100101000000000000000000000 1
1!
#2440000
0!
#2445000
b101010010100000000000000000000000 &
b10110 *
b10101001010000000000000000000000 1
1!
#2450000
0!
#2455000
b1010100101000000000000000000000000 &
b10111 *
b101010010100000000000000000000000 1
1!
#2460000
0!
#2465000
b10101001010000000000000000000000000 &
b11000 *
b1010100101000000000000000000000000 1
1!
#2470000
0!
#2475000
b101010010100000000000000000000000000 &
b11001 *
b10101001010000000000000000000000000 1
1!
#2480000
0!
#2485000
b1010100101000000000000000000000000000 &
b11010 *
b101010010100000000000000000000000000 1
1!
#2490000
0!
#2495000
b10101001010000000000000000000000000000 &
b11011 *
b1010100101000000000000000000000000000 1
1!
#2500000
0!
#2505000
b111010100000000000000000000000000010 &
b11100 *
b11101010000000000000000000000000001 1
1!
#2510000
0!
#2515000
b1110101000000000000000000000000000100 &
b11101 *
b111010100000000000000000000000000010 1
1!
#2520000
0!
#2525000
b11101010000000000000000000000000001000 &
b11110 *
b1110101000000000000000000000000000100 1
1!
#2530000
0!
#2535000
b10111100000000000000000000000000010010 &
b11111 *
b1011110000000000000000000000000001001 1
1!
#2540000
0!
#2545000
b1100000000000000000000000000000100110 &
b100000 *
b110000000000000000000000000000010011 1
1!
#2550000
0!
#2555000
b10 /
1!
#2560000
0!
#2565000
b0 /
1-
b1100 .
b10011 ,
1!
#2570000
0!
#2575000
1!
#2580000
0!
#2585000
b10010 &
b1 /
b11100 0
b1001 1
b0 *
0-
1%
b11100 #
b1001 "
1!
#2590000
0!
#2595000
b100100 &
b1 *
b10010 1
0%
1!
#2600000
0!
#2605000
b1001000 &
b10 *
b100100 1
1!
#2610000
0!
#2615000
b10010000 &
b11 *
b1001000 1
1!
#2620000
0!
#2625000
b100100000 &
b100 *
b10010000 1
1!
#2630000
0!
#2635000
b1001000000 &
b101 *
b100100000 1
1!
#2640000
0!
#2645000
b10010000000 &
b110 *
b1001000000 1
1!
#2650000
0!
#2655000
b100100000000 &
b111 *
b10010000000 1
1!
#2660000
0!
#2665000
b1001000000000 &
b1000 *
b100100000000 1
1!
#2670000
0!
#2675000
b10010000000000 &
b1001 *
b1001000000000 1
1!
#2680000
0!
#2685000
b100100000000000 &
b1010 *
b10010000000000 1
1!
#2690000
0!
#2695000
b1001000000000000 &
b1011 *
b100100000000000 1
1!
#2700000
0!
#2705000
b10010000000000000 &
b1100 *
b1001000000000000 1
1!
