rtl/storage/reg.v
`timescale 1ns / 1ps
//////////////////////////////////////////////////////////////////////////////////
// Company: 
// Engineer: 
// 
// Create Date:
// Design Name: 
// Module Name: 
// Project Name: 
// Target Devices: 
// Tool Versions: 
// Description: 
// 
// Dependencies: 
// 
// Revision:
// Revision 0.01 - File Created
// Additional Comments:
// 
//////////////////////////////////////////////////////////////////////////////////
module reg_file (
    input  wire        clk,
    input  wire        rst_n,
    input  wire        we,         // 写使能信号
    input  wire [4:0]  ra1,        // 读寄存器 1 地址
    input  wire [4:0]  ra2,        // 读寄存器 2 地址
    input  wire [4:0]  wa,         // 写寄存器地址
    input  wire [31:0] wd,         // 写数据
    output wire [31:0] rd1,        // 读数据 1
    output wire [31:0] rd2         // 读数据 2
);

    // 定义 32 个 32 位寄存器
    reg [31:0] rf [31:1]; // R0 恒为 0，所以不需要实际存储空间

    // 异步读取 (组合逻辑)
    assign rd1 = (ra1 == 5'd0) ? 32'd0 : rf[ra1];
    assign rd2 = (ra2 == 5'd0) ? 32'd0 : rf[ra2];

    // 同步写入 (时序逻辑)
    integer i;
    always @(posedge clk or negedge rst_n) begin
        if (!rst_n) begin
            // 复位时将寄存器清零 (可选，根据需求)
            for (i = 1; i < 32; i = i + 1)
                rf[i] <= 32'd0;
        end else if (we && (wa != 5'd0)) begin
            rf[wa] <= wd;
        end
    end

endmodule

sim/storage/tb_reg.v
`timescale 1ns / 1ps
//////////////////////////////////////////////////////////////////////////////////
// Company: 
// Engineer: 
// 
// Create Date:
// Design Name: 
// Module Name: 
// Project Name: 
// Target Devices: 
// Tool Versions: 
// Description: 
// 
// Dependencies: 
// 
// Revision:
// Revision 0.01 - File Created
// Additional Comments:
// 
//////////////////////////////////////////////////////////////////////////////////

module tb_reg_file();

    reg         clk;
    reg         rst_n;
    reg         we;
    reg  [4:0]  ra1, ra2, wa;
    reg  [31:0] wd;
    wire [31:0] rd1, rd2;

    // 实例化
    reg_file uut (
        .clk(clk), .rst_n(rst_n), .we(we),
        .ra1(ra1), .ra2(ra2), .wa(wa), .wd(wd),
        .rd1(rd1), .rd2(rd2)
    );

    // 时钟生成
    initial clk = 0;
    always #5 clk = ~clk;

    initial begin
        // 初始化
        rst_n = 0; we = 0; ra1 = 0; ra2 = 0; wa = 0; wd = 0;
        #20 rst_n = 1;

        $display("--- Starting RegFile Test ---");

        // 1. 测试 R0 恒零：尝试向 R0 写入数据
        @(posedge clk);
        wa = 5'd0; wd = 32'hAAAA_BBBB; we = 1;
        @(posedge clk);
        we = 0; ra1 = 5'd0;
        #1; // 等待组合逻辑稳定
        if (rd1 === 32'd0) 
            $display("[PASS] R0 is hardwired to 0.");
        else 
            $display("[FAIL] R0 was modified!");

        // 2. 基础读写测试：写入 R1, R2 并同时读出
        @(posedge clk);
        wa = 5'd1; wd = 32'h1234_5678; we = 1;
        @(posedge clk);
        wa = 5'd2; wd = 32'h8765_4321; we = 1;
        @(posedge clk);
        we = 0; ra1 = 5'd1; ra2 = 5'd2;
        #1;
        if (rd1 === 32'h1234_5678 && rd2 === 32'h8765_4321)
            $display("[PASS] Dual port read successful.");
        else
            $display("[FAIL] Read data mismatch!");

        // 3. 写使能测试：we=0 时不应写入
        @(posedge clk);
        wa = 5'd3; wd = 32'hFFFF_FFFF; we = 0; // 注意这里 we=0
        @(posedge clk);
        ra1 = 5'd3;
        #1;
        if (rd1 !== 32'hFFFF_FFFF)
            $display("[PASS] Write Enable (we) is working.");
        else
            $display("[FAIL] Data written even when we=0!");

        #20 $finish;
    end
endmodule

sim/vcd/dump_reg.vcd
$date
	Mon Aug 10 22:11:12 2026
$end
$version
	Icarus Verilog
$end
$timescale
	1ps
$end
$scope module tb_reg_file $end
$scope module uut $end
$var wire 1 ! clk $end
$var wire 5 " ra1 [4:0] $end
$var wire 5 # ra2 [4:0] $end
$var wire 1 $ rst_n $end
$var wire 5 % wa [4:0] $end
$var wire 32 & wd [31:0] $end
$var wire 1 ' we $end
$var wire 32 ( rd2 [31:0] $end
$var wire 32 ) rd1 [31:0] $end
$var integer 32 * i [31:0] $end
$upscope $end
$upscope $end
$enddefinitions $end
$comment Show the parameter values. $end
$dumpall
$end
#0
$dumpvars
b100000 *
b0 )
b0 (
0'
b0 &
b0 %
0$
b0 #
b0 "
0!
$end
#5000
b100000 *
1!
#10000
0!
#15000
b100000 *
1!
#20000
0!
1$
#25000
1'
b10101010101010101011101110111011 &
1!
#30000
0!
#35000
0'
1!
#40000
0!
#45000
1'
b10010001101000101011001111000 &
b1 %
1!
#50000
0!
#55000
b10000111011001010100001100100001 &
b10 %
1!
#60000
0!
#65000
b10000111011001010100001100100001 (
b10010001101000101011001111000 )
b10 #
b1 "
0'
1!
#70000
0!
#75000
b11111111111111111111111111111111 &
b11 %
1!
#80000
0!
#85000
b0 )
b11 "
1!
