rtl/storage/mem.v
`timescale 1ns / 1ps
//////////////////////////////////////////////////////////////////////////////////
// Company: 
// Engineer: 
// 
// Create Date:
// Design Name: 
// Module Name: mem
// Project Name: 
// Target Devices: 
// Tool Versions: 
// Description: 
// 
// Dependencies: 
// 
// Revision:
// Revision 0.01 - File Created
// Additional Comments:
// 
//////////////////////////////////////////////////////////////////////////////////
module data_mem (
    input  wire        clk,
    input  wire        we,         // 写使能
    input  wire [31:0] addr,       // 地址 (通常来自 ALU)
    input  wire [31:0] din,        // 写入的数据
    output wire [31:0] dout        // 读出的数据
);

    // 定义存储深度
    reg [31:0] ram [0:1023];

    // 同步写入
    always @(posedge clk) begin
        if (we) begin
            ram[addr[11:2]] <= din; // addr[11:2] 是因为按字寻址，忽略低两位
        end
    end

    // 异步读取 
    assign dout = ram[addr[11:2]];

endmodule

sim/storage/tb_mem.v
`timescale 1ns / 1ps
//////////////////////////////////////////////////////////////////////////////////
// Company: 
// Engineer: 
// 
// Create Date:
// Design Name: 
// Module Name: 
// Project Name: 
// Target Devices: 
// Tool Versions: 
// Description: 
// 
// Dependencies: 
// 
// Revision:
// Revision 0.01 - File Created
// Additional Comments:
// 
//////////////////////////////////////////////////////////////////////////////////
module tb_data_mem();

    reg         clk;
    reg         we;
    reg  [31:0] addr;
    reg  [31:0] din;
    wire [31:0] dout;

    // 实例化
    data_mem uut (
        .clk(clk), .we(we), .addr(addr), .din(din), .dout(dout)
    );

    initial clk = 0;
    always #5 clk = ~clk;

    initial begin
        we = 0; addr = 0; din = 0;
        #20;

        $display("--- Starting Memory Test ---");

        // 1. 基础写读测试
        @(posedge clk);
        addr = 32'h0000_0004; din = 32'hDEAD_BEEF; we = 1;
        @(posedge clk);
        we = 0;
        #1;
        if (dout === 32'hDEAD_BEEF)
            $display("[PASS] Basic Write/Read at Addr 4.");

        // 2. 字节地址对齐测试
        // 写入地址 8，尝试从地址 9, 10, 11 读取
        // 理论上 addr[11:2] 都会指向同一个槽位
        @(posedge clk);
        addr = 32'd8; din = 32'h1122_3344; we = 1;
        @(posedge clk);
        we = 0;
        
        addr = 32'd9; #1;
        if (dout === 32'h1122_3344) $display("[PASS] Addr 9 points to Word at 8.");
        
        addr = 32'd11; #1;
        if (dout === 32'h1122_3344) $display("[PASS] Addr 11 points to Word at 8.");

        // 3. 边界地址测试
        @(posedge clk);
        addr = 32'd4092; din = 32'hAAAA_5555; we = 1; // 最后一个可访问地址 (1023*4)
        @(posedge clk);
        we = 0; #1;
        if (dout === 32'hAAAA_5555)
            $display("[PASS] Boundary address (1023) check.");

        #20 $finish;
    end
endmodule

sim/vcd/dump_mem.vcd
$date
	Mon Aug 10 22:10:58 2026
$end
$version
	Icarus Verilog
$end
$timescale
	1ps
$end
$scope module tb_data_mem $end
$scope module uut $end
$var wire 32 ! addr [31:0] $end
$var wire 1 " clk $end
$var wire 32 # din [31:0] $end
$var wire 32 $ dout [31:0] $end
$var wire 1 % we $end
$upscope $end
$upscope $end
$enddefinitions $end
$comment Show the parameter values. $end
$dumpall
$end
#0
$dumpvars
0%
bx $
b0 #
0"
b0 !
$end
#5000
1"
#10000
0"
#15000
1"
#20000
0"
#25000
b11011110101011011011111011101111 $
1%
b11011110101011011011111011101111 #
b100 !
1"
#30000
0"
#35000
0%
1"
#40000
0"
#45000
b10001001000100011001101000100 $
1%
b10001001000100011001101000100 #
b1000 !
1"
#50000
0"
#55000
b1001 !
0%
1"
#56000
b1011 !
#60000
0"
#65000
b10101010101010100101010101010101 $
1%
b10101010101010100101010101010101 #
b111111111100 !
1"
#70000
0"
#75000
0%
1"
