rtl/ALU/multiplier.v
`timescale 1ns / 1ps
//////////////////////////////////////////////////////////////////////////////////
// Company: 
// Engineer: 
// 
// Create Date: 2026/03/08 14:55:15
// Design Name: 
// Module Name: multiply
// Project Name: 
// Target Devices: 
// Tool Versions: 
// Description: 
// 
// Dependencies: 
// 
// Revision:
// Revision 0.01 - File Created
// Additional Comments:
// 
//////////////////////////////////////////////////////////////////////////////////
module multiplier_seq (
    input  wire        clk,       // 系统时钟
    input  wire        rst_n,     // 异步复位，低电平有效
    input  wire        start,     // 开始计算信号 (由 CPU 发出)
    input  wire [31:0] a,         // 被乘数
    input  wire [31:0] b,         // 乘数
    output reg  [63:0] product,   // 乘法结果
    output reg         ready      // 乘法器空闲
);

    // 状态定义
    localparam IDLE = 2'b00;
    localparam CALC = 2'b01;
    localparam DONE = 2'b10;

    reg [1:0]  state;             // 状态机寄存器
    reg [5:0]  count;             // 计数器，0-32
    reg [63:0] temp_a;            // 用于移位的被乘数
    reg [31:0] temp_b;            // 用于移位的乘数

    // 状态机逻辑
    always @(posedge clk or negedge rst_n) begin
        if (!rst_n) begin
            state   <= IDLE;
            product <= 64'd0;
            ready   <= 1'b1;
            count   <= 6'd0;
            temp_a  <= 64'd0;
            temp_b  <= 32'd0;
        end else begin
            case (state)
                IDLE: begin
                    ready <= 1'b1;
                    if (start) begin
                        ready   <= 1'b0;
                        state   <= CALC;
                        count   <= 6'd0;
                        product <= 64'd0;
                        // 初始化：将被乘数扩展到64位，乘数载入临时寄存器
                        temp_a  <= {32'd0, a};
                        temp_b  <= b;
                    end
                end

                CALC: begin
                    if (count < 6'd32) begin
                        // 如果当前乘数的最低位是1，则累加 temp_a
                        if (temp_b[0]) begin
                            product <= product + temp_a;
                        end
                        // 被乘数左移，乘数右移
                        temp_a <= temp_a << 1;
                        temp_b <= temp_b >> 1;
                        count  <= count + 6'd1;
                    end else begin
                        state <= DONE;
                    end
                end

                DONE: begin
                    ready <= 1'b1;
                    state <= IDLE;
                end

                default: state <= IDLE;
            endcase
        end
    end

endmodule

sim/ALU/tb_multiplier.v
`timescale 1ns / 1ps
//////////////////////////////////////////////////////////////////////////////////
// Company: 
// Engineer: 
// 
// Create Date: 2026/03/08 14:55:35
// Design Name: 
// Module Name: tb_multiply
// Project Name: 
// Target Devices: 
// Tool Versions: 
// Description: 
// 
// Dependencies: 
// 
// Revision:
// Revision 0.01 - File Created
// Additional Comments:
// 

module tb_multiplier_seq();

    // 信号定义
    reg         clk;
    reg         rst_n;
    reg         start;
    reg  [31:0] a;
    reg  [31:0] b;
    wire [63:0] product;
    wire        ready;

    // 实例化乘法器
    multiplier_seq uut (
        .clk(clk),
        .rst_n(rst_n),
        .start(start),
        .a(a),
        .b(b),
        .product(product),
        .ready(ready)
    );

    // 1. 生成时钟：周期为 10ns
    initial clk = 0;
    always #5 clk = ~clk;

    // 2. 仿真逻辑
    initial begin
        // 初始化
        rst_n = 0;
        start = 0;
        a = 0;
        b = 0;

        // 复位动作
        #20 rst_n = 1;
        #10;

        $display("========================================");
        $display("Starting Multiplier Test...");
        $display("========================================");

        // 1: 基础乘法 ---
        drive_multiplier(32'd10, 32'd20);
        check_result("Basic Mul 10*20");

        // 2: 包含 0 ---
        drive_multiplier(32'd500, 32'd0);
        check_result("Multiply by Zero");

        // 3: 最大值测试 ---
        drive_multiplier(32'hFFFF_FFFF, 32'd1);
        check_result("Max Value * 1");

        // 4: 随机压力测试 ---
        repeat(10) begin
            drive_multiplier($urandom, $urandom);
            check_result("Random Test");
        end

        $display("========================================");
        $display("All Tests Finished.");
        $display("========================================");
        $finish;
    end

    // 任务：驱动乘法器
    task drive_multiplier(input [31:0] val_a, input [31:0] val_b);
        begin
            @(posedge clk);
            a = val_a;
            b = val_b;
            start = 1;      // 发起请求
            
            @(posedge clk);
            start = 0;      // 撤销请求，防止重复触发
            
            // 等待直到 ready 信号回到 1，表示计算完成
            wait(ready == 1); 
            @(posedge clk); // 再等一个沿，确保 product 已经稳定输出
        end
    endtask

    // 任务：检查结果
    task check_result(input [8*40:1] test_name);
        reg [63:0] expected_val;
        begin
            expected_val = a * b; // 仿真器自动计算正确值
            if (product === expected_val) begin
                $display("[PASS] %s: %d * %d = %d", test_name, a, b, product);
            end else begin
                $display("[FAIL] %s: %d * %d | Expected %d, Got %d", 
                         test_name, a, b, expected_val, product);
            end
        end
    endtask

endmodule

sim/vcd/dump_mul.vcd
$date
	Mon Aug 10 22:11:36 2026
$end
$version
	Icarus Verilog
$end
$timescale
	1ps
$end
$scope module tb_multiplier_seq $end
$scope module uut $end
$var wire 32 ! a [31:0] $end
$var wire 32 " b [31:0] $end
$var wire 1 # clk $end
$var wire 1 $ rst_n $end
$var wire 1 % start $end
$var parameter 2 & CALC $end
$var parameter 2 ' DONE $end
$var parameter 2 ( IDLE $end
$var reg 6 ) count [5:0] $end
$var reg 64 * product [63:0] $end
$var reg 1 + ready $end
$var reg 2 , state [1:0] $end
$var reg 64 - temp_a [63:0] $end
$var reg 32 . temp_b [31:0] $end
$upscope $end
$upscope $end
$enddefinitions $end
$comment Show the parameter values. $end
$dumpall
b0 (
b10 '
b1 &
$end
#0
$dumpvars
b0 .
b0 -
b0 ,
1+
b0 *
b0 )
0%
0$
0#
b0 "
b0 !
$end
#5000
1#
#10000
0#
#15000
1#
#20000
0#
1$
#25000
1#
#30000
0#
#35000
b10100 .
b1010 -
b1 ,
0+
1%
b10100 "
b1010 !
1#
#40000
0#
#45000
b1 )
b1010 .
b10100 -
0%
1#
#50000
0#
#55000
b10 )
b101 .
b101000 -
1#
#60000
0#
#65000
b11 )
b10 .
b1010000 -
b101000 *
1#
#70000
0#
#75000
b100 )
b1 .
b10100000 -
1#
#80000
0#
#85000
b101 )
b0 .
b101000000 -
b11001000 *
1#
#90000
0#
#95000
b110 )
b1010000000 -
1#
#100000
0#
#105000
b111 )
b10100000000 -
1#
#110000
0#
#115000
b1000 )
b101000000000 -
1#
#120000
0#
#125000
b1001 )
b1010000000000 -
1#
#130000
0#
#135000
b1010 )
b10100000000000 -
1#
#140000
0#
#145000
b1011 )
b101000000000000 -
1#
#150000
0#
#155000
b1100 )
b1010000000000000 -
1#
#160000
0#
#165000
b1101 )
b10100000000000000 -
1#
#170000
0#
#175000
b1110 )
b101000000000000000 -
1#
#180000
0#
#185000
b1111 )
b1010000000000000000 -
1#
#190000
0#
#195000
b10000 )
b10100000000000000000 -
1#
#200000
0#
#205000
b10001 )
b101000000000000000000 -
1#
#210000
0#
#215000
b10010 )
b1010000000000000000000 -
1#
#220000
0#
#225000
b10011 )
b10100000000000000000000 -
1#
#230000
0#
#235000
b10100 )
b101000000000000000000000 -
1#
#240000
0#
#245000
b10101 )
b1010000000000000000000000 -
1#
#250000
0#
#255000
b10110 )
b10100000000000000000000000 -
1#
#260000
0#
#265000
b10111 )
b101000000000000000000000000 -
1#
#270000
0#
#275000
b11000 )
b1010000000000000000000000000 -
1#
#280000
0#
#285000
b11001 )
b10100000000000000000000000000 -
1#
#290000
0#
#295000
b11010 )
b101000000000000000000000000000 -
1#
#300000
0#
#305000
b11011 )
b1010000000000000000000000000000 -
1#
#310000
0#
#315000
b11100 )
b10100000000000000000000000000000 -
1#
#320000
0#
#325000
b11101 )
b101000000000000000000000000000000 -
1#
#330000
0#
#335000
b11110 )
b1010000000000000000000000000000000 -
1#
#340000
0#
#345000
b11111 )
b10100000000000000000000000000000000 -
1#
#350000
0#
#355000
b100000 )
b101000000000000000000000000000000000 -
1#
#360000
0#
#365000
b10 ,
1#
#370000
0#
#375000
b0 ,
1+
1#
#380000
0#
#385000
1#
#390000
0#
#395000
b111110100 -
b0 *
b0 )
b1 ,
0+
1%
b0 "
b111110100 !
1#
#400000
0#
#405000
b1 )
b1111101000 -
0%
1#
#410000
0#
#415000
b10 )
b11111010000 -
1#
#420000
0#
#425000
b11 )
b111110100000 -
1#
#430000
0#
#435000
b100 )
b1111101000000 -
1#
#440000
0#
#445000
b101 )
b11111010000000 -
1#
#450000
0#
#455000
b110 )
b111110100000000 -
1#
#460000
0#
#465000
b111 )
b1111101000000000 -
1#
#470000
0#
#475000
b1000 )
b11111010000000000 -
1#
#480000
0#
#485000
b1001 )
b111110100000000000 -
1#
#490000
0#
#495000
b1010 )
b1111101000000000000 -
1#
#500000
0#
#505000
b1011 )
b11111010000000000000 -
1#
#510000
0#
#515000
b1100 )
b111110100000000000000 -
1#
#520000
0#
#525000
b1101 )
b1111101000000000000000 -
1#
#530000
0#
#535000
b1110 )
b11111010000000000000000 -
1#
#540000
0#
#545000
b1111 )
b111110100000000000000000 -
1#
#550000
0#
#555000
b10000 )
b1111101000000000000000000 -
1#
#560000
0#
#565000
b10001 )
b11111010000000000000000000 -
1#
#570000
0#
#575000
b10010 )
b111110100000000000000000000 -
1#
#580000
0#
#585000
b10011 )
b1111101000000000000000000000 -
1#
#590000
0#
#595000
b10100 )
b11111010000000000000000000000 -
1#
#600000
0#
#605000
b10101 )
b111110100000000000000000000000 -
1#
#610000
0#
#615000
b10110 )
b1111101000000000000000000000000 -
1#
#620000
0#
#625000
b10111 )
b11111010000000000000000000000000 -
1#
#630000
0#
#635000
b11000 )
b111110100000000000000000000000000 -
1#
#640000
0#
#645000
b11001 )
b1111101000000000000000000000000000 -
1#
#650000
0#
#655000
b11010 )
b11111010000000000000000000000000000 -
1#
#660000
0#
#665000
b11011 )
b111110100000000000000000000000000000 -
1#
#670000
0#
#675000
b11100 )
b1111101000000000000000000000000000000 -
1#
#680000
0#
#685000
b11101 )
b11111010000000000000000000000000000000 -
1#
#690000
0#
#695000
b11110 )
b111110100000000000000000000000000000000 -
1#
#700000
0#
#705000
b11111 )
b1111101000000000000000000000000000000000 -
1#
#710000
0#
#715000
b100000 )
b11111010000000000000000000000000000000000 -
1#
#720000
0#
#725000
b10 ,
1#
#730000
0#
#735000
b0 ,
1+
1#
#740000
0#
#745000
1#
#750000
0#
#755000
b1 .
b11111111111111111111111111111111 -
b0 )
b1 ,
0+
1%
b1 "
b11111111111111111111111111111111 !
1#
#760000
0#
#765000
b1 )
b0 .
b111111111111111111111111111111110 -
b11111111111111111111111111111111 *
0%
1#
#770000
0#
#775000
b10 )
b1111111111111111111111111111111100 -
1#
#780000
0#
#785000
b11 )
b11111111111111111111111111111111000 -
1#
#790000
0#
#795000
b100 )
b111111111111111111111111111111110000 -
1#
#800000
0#
#805000
b101 )
b1111111111111111111111111111111100000 -
1#
#810000
0#
#815000
b110 )
b11111111111111111111111111111111000000 -
1#
#820000
0#
#825000
b111 )
b111111111111111111111111111111110000000 -
1#
#830000
0#
#835000
b1000 )
b1111111111111111111111111111111100000000 -
1#
#840000
0#
#845000
b1001 )
b11111111111111111111111111111111000000000 -
1#
#850000
0#
#855000
b1010 )
b111111111111111111111111111111110000000000 -
1#
#860000
0#
#865000
b1011 )
b1111111111111111111111111111111100000000000 -
1#
#870000
0#
#875000
b1100 )
b11111111111111111111111111111111000000000000 -
1#
#880000
0#
#885000
b1101 )
b111111111111111111111111111111110000000000000 -
1#
#890000
0#
#895000
b1110 )
b1111111111111111111111111111111100000000000000 -
1#
#900000
0#
#905000
b1111 )
b11111111111111111111111111111111000000000000000 -
1#
#910000
0#
#915000
b10000 )
b111111111111111111111111111111110000000000000000 -
1#
#920000
0#
#925000
b10001 )
b1111111111111111111111111111111100000000000000000 -
1#
#930000
0#
#935000
b10010 )
b11111111111111111111111111111111000000000000000000 -
1#
#940000
0#
#945000
b10011 )
b111111111111111111111111111111110000000000000000000 -
1#
#950000
0#
#955000
b10100 )
b1111111111111111111111111111111100000000000000000000 -
1#
#960000
0#
#965000
b10101 )
b11111111111111111111111111111111000000000000000000000 -
1#
#970000
0#
#975000
b10110 )
b111111111111111111111111111111110000000000000000000000 -
1#
#980000
0#
#985000
b10111 )
b1111111111111111111111111111111100000000000000000000000 -
1#
#990000
0#
#995000
b11000 )
b11111111111111111111111111111111000000000000000000000000 -
1#
#1000000
0#
#1005000
b11001 )
b111111111111111111111111111111110000000000000000000000000 -
1#
#1010000
0#
#1015000
b11010 )
b1111111111111111111111111111111100000000000000000000000000 -
1#
#1020000
0#
#1025000
b11011 )
b11111111111111111111111111111111000000000000000000000000000 -
1#
#1030000
0#
#1035000
b11100 )
b111111111111111111111111111111110000000000000000000000000000 -
1#
#1040000
0#
#1045000
b11101 )
b1111111111111111111111111111111100000000000000000000000000000 -
1#
#1050000
0#
#1055000
b11110 )
b11111111111111111111111111111111000000000000000000000000000000 -
1#
#1060000
0#
#1065000
b11111 )
b111111111111111111111111111111110000000000000000000000000000000 -
1#
#1070000
0#
#1075000
b100000 )
b1111111111111111111111111111111100000000000000000000000000000000 -
1#
#1080000
0#
#1085000
b10 ,
1#
#1090000
0#
#1095000
b0 ,
1+
1#
#1100000
0#
#1105000
1#
#1110000
0#
#1115000
b1000000100010010101111010000001 .
b10010010000101010011010100100100 -
b0 *
b0 )
b1 ,
0+
1%
b1000000100010010101111010000001 "
b10010010000101010011010100100100 !
1#
#1120000
0#
#1125000
b1 )
b100000010001001010111101000000 .
b100100100001010100110101001001000 -
b10010010000101010011010100100100 *
0%
1#
#1130000
0#
#1135000
b10 )
b10000001000100101011110100000 .
b1001001000010101001101010010010000 -
1#
#1140000
0#
#1145000
b11 )
b1000000100010010101111010000 .
b10010010000101010011010100100100000 -
1#
#1150000
0#
#1155000
b100 )
b100000010001001010111101000 .
b100100100001010100110101001001000000 -
1#
#1160000
0#
#1165000
b101 )
b10000001000100101011110100 .
b1001001000010101001101010010010000000 -
1#
#1170000
0#
#1175000
b110 )
b1000000100010010101111010 .
b10010010000101010011010100100100000000 -
1#
#1180000
0#
#1185000
b111 )
b100000010001001010111101 .
b100100100001010100110101001001000000000 -
1#
#1190000
0#
#1195000
b1000 )
b10000001000100101011110 .
b1001001000010101001101010010010000000000 -
b100100110011100101011111100011100100100 *
1#
#1200000
0#
#1205000
b1001 )
b1000000100010010101111 .
b10010010000101010011010100100100000000000 -
1#
#1210000
0#
#1215000
b1010 )
b100000010001001010111 .
b100100100001010100110101001001000000000000 -
b10110110111000111000110100000111100100100 *
1#
#1220000
0#
#1225000
b1011 )
b10000001000100101011 .
b1001001000010101001101010010010000000000000 -
b111011011000011011111011101001111100100100 *
1#
#1230000
0#
#1235000
b1100 )
b1000000100010010101 .
b10010010000101010011010100100100000000000000 -
b10000100011011000101100101111011111100100100 *
1#
#1240000
0#
#1245000
b1101 )
b100000010001001010 .
b100100100001010100110101001001000000000000000 -
b100010110100000011000111010011111111100100100 *
1#
#1250000
0#
#1255000
b1110 )
b10000001000100101 .
b1001001000010101001101010010010000000000000000 -
1#
#1260000
0#
#1265000
b1111 )
b1000000100010010 .
b10010010000101010011010100100100000000000000000 -
b1101011110110101100110001100101111111100100100 *
1#
#1270000
0#
#1275000
b10000 )
b100000010001001 .
b100100100001010100110101001001000000000000000000 -
1#
#1280000
0#
#1285000
b10001 )
b10000001000100 .
b1001001000010101001101010010010000000000000000000 -
b110010000000001010011011010101101111111100100100 *
1#
#1290000
0#
#1295000
b10010 )
b1000000100010 .
b10010010000101010011010100100100000000000000000000 -
1#
#1300000
0#
#1305000
b10011 )
b100000010001 .
b100100100001010100110101001001000000000000000000000 -
1#
#1310000
0#
#1315000
b10100 )
b10000001000 .
b1001001000010101001101010010010000000000000000000000 -
b101010110001010110001000100011101101111111100100100 *
1#
#1320000
0#
#1325000
b10101 )
b1000000100 .
b10010010000101010011010100100100000000000000000000000 -
1#
#1330000
0#
#1335000
b10110 )
b100000010 .
b100100100001010100110101001001000000000000000000000000 -
1#
#1340000
0#
#1345000
b10111 )
b10000001 .
b1001001000010101001101010010010000000000000000000000000 -
1#
#1350000
0#
#1355000
b11000 )
b1000000 .
b10010010000101010011010100100100000000000000000000000000 -
b1001110011000110100011011010110011101101111111100100100 *
1#
#1360000
0#
#1365000
b11001 )
b100000 .
b100100100001010100110101001001000000000000000000000000000 -
1#
#1370000
0#
#1375000
b11010 )
b10000 .
b1001001000010101001101010010010000000000000000000000000000 -
1#
#1380000
0#
#1385000
b11011 )
b1000 .
b10010010000101010011010100100100000000000000000000000000000 -
1#
#1390000
0#
#1395000
b11100 )
b100 .
b100100100001010100110101001001000000000000000000000000000000 -
1#
#1400000
0#
#1405000
b11101 )
b10 .
b1001001000010101001101010010010000000000000000000000000000000 -
1#
#1410000
0#
#1415000
b11110 )
b1 .
b10010010000101010011010100100100000000000000000000000000000000 -
1#
#1420000
0#
#1425000
b11111 )
b0 .
b100100100001010100110101001001000000000000000000000000000000000 -
b10010011010011101100001000111111010110011101101111111100100100 *
1#
#1430000
0#
#1435000
b100000 )
b1001001000010101001101010010010000000000000000000000000000000000 -
1#
#1440000
0#
#1445000
b10 ,
1#
#1450000
0#
#1455000
b0 ,
1+
1#
#1460000
0#
#1465000
1#
#1470000
0#
#1475000
b110001111100000101011001100011 .
b100100001001101011000001001 -
b0 *
b0 )
b1 ,
0+
1%
b110001111100000101011001100011 "
b100100001001101011000001001 !
1#
#1480000
0#
#1485000
b1 )
b11000111110000010101100110001 .
b1001000010011010110000010010 -
b100100001001101011000001001 *
0%
1#
#1490000
0#
#1495000
b10 )
b1100011111000001010110011000 .
b10010000100110101100000100100 -
b1101100011101000001000011011 *
1#
#1500000
0#
#1505000
b11 )
b110001111100000101011001100 .
b100100001001101011000001001000 -
1#
#1510000
0#
#1515000
b100 )
b11000111110000010101100110 .
b1001000010011010110000010010000 -
1#
#1520000
0#
#1525000
b101 )
b1100011111000001010110011 .
b10010000100110101100000100100000 -
1#
#1530000
0#
#1535000
b110 )
b110001111100000101011001 .
b100100001001101011000001001000000 -
b10011110001010010100001100111011 *
1#
#1540000
0#
#1545000
b111 )
b11000111110000010101100 .
b1001000010011010110000010010000000 -
b110111111010111101100010101111011 *
1#
#1550000
0#
#1555000
b1000 )
b1100011111000001010110 .
b10010000100110101100000100100000000 -
1#
#1560000
0#
#1565000
b1001 )
b110001111100000101011 .
b100100001001101011000001001000000000 -
1#
#1570000
0#
#1575000
b1010 )
b11000111110000010101 .
b1001000010011010110000010010000000000 -
b101011001001000010101101011101111011 *
1#
#1580000
0#
#1585000
b1011 )
b1100011111000001010 .
b10010000100110101100000100100000000000 -
b1110011011100011000101111101101111011 *
1#
#1590000
0#
#1595000
b1100 )
b110001111100000101 .
b100100001001101011000001001000000000000 -
1#
#1600000
0#
#1605000
b1101 )
b11000111110000010 .
b1001000010011010110000010010000000000000 -
b110010100101001110000111000101101111011 *
1#
#1610000
0#
#1615000
b1110 )
b1100011111000001 .
b10010000100110101100000100100000000000000 -
1#
#1620000
0#
#1625000
b1111 )
b110001111100000 .
b100100001001101011000001001000000000000000 -
b11000011001011111010001011100101101111011 *
1#
#1630000
0#
#1635000
b10000 )
b11000111110000 .
b1001000010011010110000010010000000000000000 -
1#
#1640000
0#
#1645000
b10001 )
b1100011111000 .
b10010000100110101100000100100000000000000000 -
1#
#1650000
0#
#1655000
b10010 )
b110001111100 .
b100100001001101011000001001000000000000000000 -
1#
#1660000
0#
#1665000
b10011 )
b11000111110 .
b1001000010011010110000010010000000000000000000 -
1#
#1670000
0#
#1675000
b10100 )
b1100011111 .
b10010000100110101100000100100000000000000000000 -
1#
#1680000
0#
#1685000
b10101 )
b110001111 .
b100100001001101011000001001000000000000000000000 -
b10010011101001110111111110101011100101101111011 *
1#
#1690000
0#
#1695000
b10110 )
b11000111 .
b1001000010011010110000010010000000000000000000000 -
b110110100110111010000000111101011100101101111011 *
1#
#1700000
0#
#1705000
b10111 )
b1100011 .
b10010000100110101100000100100000000000000000000000 -
b1111110111010010000000011001101011100101101111011 *
1#
#1710000
0#
#1715000
b11000 )
b110001 .
b100100001001101011000001001000000000000000000000000 -
b100001111100000111100000111101101011100101101111011 *
1#
#1720000
0#
#1725000
b11001 )
b11000 .
b1001000010011010110000010010000000000000000000000000 -
b1000110000101110010100010000101101011100101101111011 *
1#
#1730000
0#
#1735000
b11010 )
b1100 .
b10010000100110101100000100100000000000000000000000000 -
1#
#1740000
0#
#1745000
b11011 )
b110 .
b100100001001101011000001001000000000000000000000000000 -
1#
#1750000
0#
#1755000
b11100 )
b11 .
b1001000010011010110000010010000000000000000000000000000 -
1#
#1760000
0#
#1765000
b11101 )
b1 .
b10010000100110101100000100100000000000000000000000000000 -
b1010001000100000100010110100000101101011100101101111011 *
1#
#1770000
0#
#1775000
b11110 )
b0 .
b100100001001101011000001001000000000000000000000000000000 -
b11100001101010110000011011000000101101011100101101111011 *
1#
#1780000
0#
#1785000
b11111 )
b1001000010011010110000010010000000000000000000000000000000 -
1#
#1790000
0#
#1795000
b100000 )
b10010000100110101100000100100000000000000000000000000000000 -
1#
#1800000
0#
#1805000
b10 ,
1#
#1810000
0#
#1815000
b0 ,
1+
1#
#1820000
0#
#1825000
1#
#1830000
0#
#1835000
b11000110110111111001100110001101 .
b10000110101110010111101100001101 -
b0 *
b0 )
b1 ,
0+
1%
b11000110110111111001100110001101 "
b10000110101110010111101100001101 !
1#
#1840000
0#
#1845000
b1 )
b1100011011011111100110011000110 .
b100001101011100101111011000011010 -
b10000110101110010111101100001101 *
0%
1#
#1850000
0#
#1855000
b10 )
b110001101101111110011001100011 .
b1000011010111001011110110000110100 -
1#
#1860000
0#
#1865000
b11 )
b11000110110111111001100110001 .
b10000110101110010111101100001101000 -
b1010100001100111110110011101000001 *
1#
#1870000
0#
#1875000
b100 )
b1100011011011111100110011000 .
b100001101011100101111011000011010000 -
b11011010111011010110011111110101001 *
1#
#1880000
0#
#1885000
b101 )
b110001101101111110011001100 .
b1000011010111001011110110000110100000 -
1#
#1890000
0#
#1895000
b110 )
b11000110110111111001100110 .
b10000110101110010111101100001101000000 -
1#
#1900000
0#
#1905000
b111 )
b1100011011011111100110011 .
b100001101011100101111011000011010000000 -
1#
#1910000
0#
#1915000
b1000 )
b110001101101111110011001 .
b1000011010111001011110110000110100000000 -
b100101000110100001010001100011000101001 *
1#
#1920000
0#
#1925000
b1001 )
b11000110110111111001100 .
b10000110101110010111101100001101000000000 -
b1101000011101101101000111101001100101001 *
1#
#1930000
0#
#1935000
b1010 )
b1100011011011111100110 .
b100001101011100101111011000011010000000000 -
1#
#1940000
0#
#1945000
b1011 )
b110001101101111110011 .
b1000011010111001011110110000110100000000000 -
1#
#1950000
0#
#1955000
b1100 )
b11000110110111111001 .
b10000110101110010111101100001101000000000000 -
b1010000011010111001011111000011101100101001 *
1#
#1960000
0#
#1965000
b1101 )
b1100011011011111100 .
b100001101011100101111011000011010000000000000 -
b11010111001001010001001011010000101100101001 *
1#
#1970000
0#
#1975000
b1110 )
b110001101101111110 .
b1000011010111001011110110000110100000000000000 -
1#
#1980000
0#
#1985000
b1111 )
b11000110110111111 .
b10000110101110010111101100001101000000000000000 -
1#
#1990000
0#
#1995000
b10000 )
b1100011011011111 .
b100001101011100101111011000011010000000000000000 -
b10100001100111100001110101100111000101100101001 *
1#
#2000000
0#
#2005000
b10001 )
b110001101101111 .
b1000011010111001011110110000110100000000000000000 -
b110101111000100010001001110000001000101100101001 *
1#
#2010000
0#
#2015000
b10010 )
b11000110110111 .
b10000110101110010111101100001101000000000000000000 -
b1111001001111101101111111110110101000101100101001 *
1#
#2020000
0#
#2025000
b10011 )
b1100011011011 .
b100001101011100101111011000011010000000000000000000 -
b11111111111110000101101100000011101000101100101001 *
1#
#2030000
0#
#2035000
b10100 )
b110001101101 .
b1000011010111001011110110000110100000000000000000000 -
b1000001101011010110101000100011101101000101100101001 *
1#
#2040000
0#
#2045000
b10101 )
b11000110110 .
b10000110101110010111101100001101000000000000000000000 -
b10000101000010100010011110101010001101000101100101001 *
1#
#2050000
0#
#2055000
b10110 )
b1100011011 .
b100001101011100101111011000011010000000000000000000000 -
1#
#2060000
0#
#2065000
b10111 )
b110001101 .
b1000011010111001011110110000110100000000000000000000000 -
b110010010011111010001110111000100001101000101100101001 *
1#
#2070000
0#
#2075000
b11000 )
b11000110 .
b10000110101110010111101100001101000000000000000000000000 -
b1110101101011000110000100111111000001101000101100101001 *
1#
#2080000
0#
#2085000
b11001 )
b1100011 .
b100001101011100101111011000011010000000000000000000000000 -
1#
#2090000
0#
#2095000
b11010 )
b110001 .
b1000011010111001011110110000110100000000000000000000000000 -
b110000011000111110101011101011001000001101000101100101001 *
1#
#2100000
0#
#2105000
b11011 )
b11000 .
b10000110101110010111101100001101000000000000000000000000000 -
b1110011110000001010100001110001101000001101000101100101001 *
1#
#2110000
0#
#2115000
b11100 )
b1100 .
b100001101011100101111011000011010000000000000000000000000000 -
1#
#2120000
0#
#2125000
b11101 )
b110 .
b1000011010111001011110110000110100000000000000000000000000000 -
1#
#2130000
0#
#2135000
b11110 )
b11 .
b10000110101110010111101100001101000000000000000000000000000000 -
1#
#2140000
0#
#2145000
b11111 )
b1 .
b100001101011100101111011000011010000000000000000000000000000000 -
b10010101001100011001000000011011001101000001101000101100101001 *
1#
#2150000
0#
#2155000
b100000 )
b0 .
b1000011010111001011110110000110100000000000000000000000000000000 -
b110100010101001001000011000110101001101000001101000101100101001 *
1#
#2160000
0#
#2165000
b10 ,
1#
#2170000
0#
#2175000
b0 ,
1+
1#
#2180000
0#
#2185000
1#
#2190000
0#
#2195000
b1001001101110101001000010010 .
b110010110000101000010001100101 -
b0 *
b0 )
b1 ,
0+
1%
b1001001101110101001000010010 "
b110010110000101000010001100101 !
1#
#2200000
0#
#2205000
b1 )
b100100110111010100100001001 .
b1100101100001010000100011001010 -
0%
1#
#2210000
0#
#2215000
b10 )
b10010011011101010010000100 .
b11001011000010100001000110010100 -
b1100101100001010000100011001010 *
1#
#2220000
0#
#2225000
b11 )
b1001001101110101001000010 .
b110010110000101000010001100101000 -
1#
#2230000
0#
#2235000
b100 )
b100100110111010100100001 .
b1100101100001010000100011001010000 -
1#
#2240000
0#
#2245000
b101 )
b10010011011101010010000 .
b11001011000010100001000110010100000 -
b1110010001101011010100111100011010 *
1#
#2250000
0#
#2255000
b110 )
b1001001101110101001000 .
b110010110000101000010001100101000000 -
1#
#2260000
0#
#2265000
b111 )
b100100110111010100100 .
b1100101100001010000100011001010000000 -
1#
#2270000
0#
#2275000
b1000 )
b10010011011101010010 .
b11001011000010100001000110010100000000 -
1#
#2280000
0#
#2285000
b1001 )
b1001001101110101001 .
b110010110000101000010001100101000000000 -
1#
#2290000
0#
#2295000
b1010 )
b100100110111010100 .
b1100101100001010000100011001010000000000 -
b110100100010110101101100001100100011010 *
1#
#2300000
0#
#2305000
b1011 )
b10010011011101010 .
b11001011000010100001000110010100000000000 -
1#
#2310000
0#
#2315000
b1100 )
b1001001101110101 .
b110010110000101000010001100101000000000000 -
1#
#2320000
0#
#2325000
b1101 )
b100100110111010 .
b1100101100001010000100011001010000000000000 -
b111001010100111110111111000110100100011010 *
1#
#2330000
0#
#2335000
b1110 )
b10010011011101 .
b11001011000010100001000110010100000000000000 -
1#
#2340000
0#
#2345000
b1111 )
b1001001101110 .
b110010110000101000010001100101000000000000000 -
b100000100010111100000000101011010100100011010 *
1#
#2350000
0#
#2355000
b10000 )
b100100110111 .
b1100101100001010000100011001010000000000000000 -
1#
#2360000
0#
#2365000
b10001 )
b10010011011 .
b11001011000010100001000110010100000000000000000 -
b10000110000100001100100011110101010100100011010 *
1#
#2370000
0#
#2375000
b10010 )
b1001001101 .
b110010110000101000010001100101000000000000000000 -
b101010001000110101101101010001001010100100011010 *
1#
#2380000
0#
#2385000
b10011 )
b100100110 .
b1100101100001010000100011001010000000000000000000 -
b1011100111001011101111110110110001010100100011010 *
1#
#2390000
0#
#2395000
b10100 )
b10010011 .
b11001011000010100001000110010100000000000000000000 -
1#
#2400000
0#
#2405000
b10101 )
b1001001 .
b110010110000101000010001100101000000000000000000000 -
b100100111111011111111000101001010001010100100011010 *
1#
#2410000
0#
#2415000
b10110 )
b100100 .
b1100101100001010000100011001010000000000000000000000 -
b1010111110000001000001010001110010001010100100011010 *
1#
#2420000
0#
#2425000
b10111 )
b10010 .
b11001011000010100001000110010100000000000000000000000 -
1#
#2430000
0#
#2435000
b11000 )
b1001 .
b110010110000101000010001100101000000000000000000000000 -
1#
#2440000
0#
#2445000
b11001 )
b100 .
b1100101100001010000100011001010000000000000000000000000 -
b111101101110101001010010110110110010001010100100011010 *
1#
#2450000
0#
#2455000
b11010 )
b10 .
b11001011000010100001000110010100000000000000000000000000 -
1#
#2460000
0#
#2465000
b11011 )
b1 .
b110010110000101000010001100101000000000000000000000000000 -
1#
#2470000
0#
#2475000
b11100 )
b0 .
b1100101100001010000100011001010000000000000000000000000000 -
b111010011110011101011011111011110110010001010100100011010 *
1#
#2480000
0#
#2485000
b11101 )
b11001011000010100001000110010100000000000000000000000000000 -
1#
#2490000
0#
#2495000
b11110 )
b110010110000101000010001100101000000000000000000000000000000 -
1#
#2500000
0#
#2505000
b11111 )
b1100101100001010000100011001010000000000000000000000000000000 -
1#
#2510000
0#
#2515000
b100000 )
b11001011000010100001000110010100000000000000000000000000000000 -
1#
#2520000
0#
#2525000
b10 ,
1#
#2530000
0#
#2535000
b0 ,
1+
1#
#2540000
0#
#2545000
1#
#2550000
0#
#2555000
b10000110110101111100110100001101 .
b10000000111100111110001100000001 -
b0 *
b0 )
b1 ,
0+
1%
b10000110110101111100110100001101 "
b10000000111100111110001100000001 !
1#
#2560000
0#
#2565000
b1 )
b1000011011010111110011010000110 .
b100000001111001111100011000000010 -
b10000000111100111110001100000001 *
0%
1#
#2570000
0#
#2575000
b10 )
b100001101101011111001101000011 .
b1000000011110011111000110000000100 -
1#
#2580000
0#
#2585000
b11 )
b10000110110101111100110100001 .
b10000000111100111110001100000001000 -
b1010000100110000110110111100000101 *
1#
#2590000
0#
